nuntius/__init__.py
nuntius/actions.py
nuntius/admin/__init__.py
nuntius/admin/fields.py
nuntius/admin/panels.py
nuntius/admin/push_panels.py
nuntius/app_settings.py
nuntius/apps.py
nuntius/locale/fr/LC_MESSAGES/django.po
nuntius/management/__init__.py
nuntius/management/commands/__init__.py
nuntius/management/commands/nuntius_worker.py
nuntius/messages.py
nuntius/migrations/0001_initial.py
nuntius/migrations/0002_add_mosaico.py
nuntius/migrations/0003_allow_no_segments.py
nuntius/migrations/0004_add_esp_id.py
nuntius/migrations/0005_change_status_choices.py
nuntius/migrations/0006_subscriber_verbose_name.py
nuntius/migrations/0007_message_content_text_blank.py
nuntius/migrations/0008_campaign_first_sent.py
nuntius/migrations/0009_verbose_names.py
nuntius/migrations/0010_verbose_names.py
nuntius/migrations/0011_open_click_counts.py
nuntius/migrations/0012_campaignsentevent_tracking_id.py
nuntius/migrations/0013_esp_message_id_not_editable.py
nuntius/migrations/0014_campaign_signature_key.py
nuntius/migrations/0015_only_one_segment_model.py
nuntius/migrations/0016_indices_and_ordering.py
nuntius/migrations/0017_campaign_utm_name.py
nuntius/migrations/0018_remove_campaign_task_uuid.py
nuntius/migrations/0019_add_tracking_index.py
nuntius/migrations/0020_auto_20210118_1100.py
nuntius/migrations/0021_create_push_campaign_models.py
nuntius/migrations/0022_add_start_and_end_dates_to_campaigns.py
nuntius/migrations/0023_add_help_text_to_pushcampaign_notification_tag.py
nuntius/migrations/0024_alter_mosaicoimage_file.py
nuntius/migrations/__init__.py
nuntius/models/__init__.py
nuntius/models/email_campaigns.py
nuntius/models/mixins.py
nuntius/models/push_campaigns.py
nuntius/models/subscriber.py
nuntius/signals.py
nuntius/static/nuntius/js.cookie.js
nuntius/static/nuntius/mosaico/fontawesome/fontawesome-webfont.eot
nuntius/static/nuntius/mosaico/fontawesome/fontawesome-webfont.svg
nuntius/static/nuntius/mosaico/fontawesome/fontawesome-webfont.ttf
nuntius-2.5.0.dist-info/LICENSE
nuntius-2.5.0.dist-info/METADATA
nuntius-2.5.0.dist-info/WHEEL
nuntius-2.5.0.dist-info/RECORD
