Metadata-Version: 2.1
Name: nuntius
Version: 2.5.0
Summary: A newsletter app to be used with Django or standalone.
Home-page: https://github.com/lafranceinsoumise/nuntius
License: GPLv3
Author: Jill Royer
Author-email: hello@jillroyer.me
Requires-Python: >=3.8,<4.0
Classifier: Development Status :: 4 - Beta
Classifier: Environment :: Web Environment
Classifier: Framework :: Django
Classifier: Framework :: Django :: 2.0
Classifier: Intended Audience :: Developers
Classifier: License :: OSI Approved :: GNU General Public License v3 (GPLv3)
Classifier: License :: Other/Proprietary License
Classifier: Operating System :: OS Independent
Classifier: Programming Language :: Python
Classifier: Programming Language :: Python :: 3
Classifier: Programming Language :: Python :: 3.8
Classifier: Programming Language :: Python :: 3.9
Classifier: Programming Language :: Python :: 3.10
Classifier: Programming Language :: Python :: 3.11
Classifier: Programming Language :: Python :: 3.12
Classifier: Programming Language :: Python :: 3.6
Classifier: Programming Language :: Python :: 3.7
Classifier: Topic :: Communications :: Email
Classifier: Topic :: Internet :: WWW/HTTP
Classifier: Topic :: Internet :: WWW/HTTP :: Dynamic Content
Provides-Extra: anymail
Provides-Extra: mysql
Provides-Extra: push
Requires-Dist: Django (>=2.0)
Requires-Dist: Pillow (>=9.0.1)
Requires-Dist: apns (>=2.0.1) ; extra == "push"
Requires-Dist: boto3 ; extra == "anymail"
Requires-Dist: dj-database-url (>=1.2.0)
Requires-Dist: django-anymail ; extra == "anymail"
Requires-Dist: django-push-notifications (>=2.0.0) ; extra == "push"
Requires-Dist: django-stdimage
Requires-Dist: inscriptis (==2.5.*)
Requires-Dist: mysqlclient ; extra == "mysql"
Requires-Dist: pillow (==10.1.0)
Requires-Dist: pywebpush (>=1.14.0) ; extra == "push"
Requires-Dist: tenacity
Project-URL: Repository, https://github.com/lafranceinsoumise/nuntius
